freeneiroapi/__init__.py
freeneiroapi/api.py
freeneiroapi-0.3.dist-info/LICENSE
freeneiroapi-0.3.dist-info/METADATA
freeneiroapi-0.3.dist-info/WHEEL
freeneiroapi-0.3.dist-info/top_level.txt
freeneiroapi-0.3.dist-info/RECORD
